README.rst
peewee_mssql.py
setup.py
peewee_mssql.egg-info/PKG-INFO
peewee_mssql.egg-info/SOURCES.txt
peewee_mssql.egg-info/dependency_links.txt
peewee_mssql.egg-info/requires.txt
peewee_mssql.egg-info/top_level.txt