Metadata-Version: 1.1
Name: peewee-mssql
Version: 0.1.3
Summary: Database driver to add Microsoft SQL Server/Azure support to Peewee
Home-page: https://github.com/cour4g3/peewee-mssql
Author: Michael de Villiers
Author-email: michael@cour4g3.me
License: MIT
Platform: any
Classifier: Development Status :: 3 - Alpha
Classifier: Intended Audience :: Developers
Classifier: License :: OSI Approved :: MIT License
Classifier: Operating System :: OS Independent
Classifier: Programming Language :: Python
Classifier: Topic :: Software Development :: Libraries :: Python Modules
Classifier: Programming Language :: Python :: 2.7
Classifier: Programming Language :: Python :: 2.6
Classifier: Programming Language :: Python :: 3.3
Classifier: Programming Language :: Python :: 3.4
Classifier: Programming Language :: Python :: 3.5
